[
  {
    "id": 4,
    "title": "PlaceSure, an enhance travel experience with AI",
    "date": "2024",
    "description": "A mobile app designed to enhance the experience of tourists and travelers, through their trips through cities around the world.",
    "image": "project_4",
    "alt_text": "project_4",
    "categories": "Product Design"
  },
  {
    "id": 3,
    "title": "Design System for Spain Government",
    "date": "2024",
    "description": "Building a cohesive Government experience for spanish citizens. To make the user's life easier.",
    "image": "project_3_big",
    "alt_text": "project_3_big",
    "categories": "Product Design"
  },
  {
    "id": 1,
    "title": "Developing the app for a food on time information service",
    "date": "2022",
    "description": "Food on time is a seasoned fruits and veggies app for a better life. Oriented to the main idea to make more accessible this healthy info.",
    "image": "project_1_big",
    "alt_text": "project_1_big",
    "categories": "Product Design"
  }
]